README.rst
setup.cfg
setup.py
dummy_data/__init__.py
dummy_data/data.py
dummy_data/dummy_random.py
dummy_data.egg-info/PKG-INFO
dummy_data.egg-info/SOURCES.txt
dummy_data.egg-info/dependency_links.txt
dummy_data.egg-info/not-zip-safe
dummy_data.egg-info/requires.txt
dummy_data.egg-info/top_level.txt