Metadata-Version: 1.0
Name: dummy-data
Version: 0.0.3
Summary: Create dummy data dynamically.
Home-page: http://github.com/deaps/dummy_data
Author: João Andrade
Author-email: joaoandrade2@protonmail.com
License: MIT
Keywords: dummy files,dummy folders,filesystem
Platform: UNKNOWN
